unified_finance_data/__init__.py
unified_finance_data/constants.py
unified_finance_data/core.py
unified_finance_data/exceptions.py
unified_finance_data/crawlers/__init__.py
unified_finance_data/crawlers/baidu_api.py
unified_finance_data/crawlers/baidu_playwright.py
unified_finance_data/crawlers/sina_kline.py
unified_finance_data/crawlers/ths_kline.py
unified_finance_data-1.0.1.dist-info/licenses/LICENSE
unified_finance_data-1.0.1.dist-info/METADATA
unified_finance_data-1.0.1.dist-info/WHEEL
unified_finance_data-1.0.1.dist-info/top_level.txt
unified_finance_data-1.0.1.dist-info/RECORD
